README.md
setup.py
permutation_flowshop.egg-info/PKG-INFO
permutation_flowshop.egg-info/SOURCES.txt
permutation_flowshop.egg-info/dependency_links.txt
permutation_flowshop.egg-info/requires.txt
permutation_flowshop.egg-info/top_level.txt
pfsp/NEH.py
pfsp/NEHT.py
pfsp/__init__.py
pfsp/calculate_makespan.py
pfsp/earliest_time_makespan_calculate.py
pfsp/gantt.py
pfsp/local_search.py
pfsp/metaheuristics.py
pfsp/read_file.py
pfsp/validations.py