Metadata-Version: 2.1
Name: permutation-flowshop
Version: 1.0.1
Summary: Package to facilitate studies about Permutation Flow Shop Scheduling Problem (PFSP)
Author: Bruno, Raphael
Author-email: bruno.development3@gmail.com
Keywords: permutation flowshop
Classifier: Programming Language :: Python :: 3
Classifier: Operating System :: OS Independent
Requires-Python: >=3.10
Requires-Dist: pandas
Requires-Dist: numpy
Requires-Dist: plotly
